{
"meta":{"test_sets":[],"test_metrics":[],"learn_metrics":[{"best_value":"Min","name":"Logloss"}],"launch_mode":"Train","parameters":"","iteration_count":200,"learn_sets":["learn"],"name":"experiment"},
"iterations":[
{"learn":[0.6834663427],"iteration":0,"passed_time":0.0009808204164,"remaining_time":0.1951832629},
{"learn":[0.6670627786],"iteration":1,"passed_time":0.001607480776,"remaining_time":0.1591405968},
{"learn":[0.6551207488],"iteration":2,"passed_time":0.002209455892,"remaining_time":0.1450876036},
{"learn":[0.6437512433],"iteration":3,"passed_time":0.002868802423,"remaining_time":0.1405713187},
{"learn":[0.6307377596],"iteration":4,"passed_time":0.00397620363,"remaining_time":0.1550719416},
{"learn":[0.6218023973],"iteration":5,"passed_time":0.004684160964,"remaining_time":0.1514545378},
{"learn":[0.6133615622],"iteration":6,"passed_time":0.005402544647,"remaining_time":0.1489558738},
{"learn":[0.6083241106],"iteration":7,"passed_time":0.006043420797,"remaining_time":0.1450420991},
{"learn":[0.5949701157],"iteration":8,"passed_time":0.006646108903,"remaining_time":0.1410452001},
{"learn":[0.5875779289],"iteration":9,"passed_time":0.007245809457,"remaining_time":0.1376703797},
{"learn":[0.5847846858],"iteration":10,"passed_time":0.007889590545,"remaining_time":0.1355575103},
{"learn":[0.5768264705],"iteration":11,"passed_time":0.008517841212,"remaining_time":0.133446179},
{"learn":[0.5692532959],"iteration":12,"passed_time":0.009143006449,"remaining_time":0.1315186312},
{"learn":[0.5636067455],"iteration":13,"passed_time":0.009976352067,"remaining_time":0.1325429632},
{"learn":[0.5605036927],"iteration":14,"passed_time":0.01079661963,"remaining_time":0.1331583087},
{"learn":[0.5552197974],"iteration":15,"passed_time":0.01142224911,"remaining_time":0.1313558648},
{"learn":[0.5513319406],"iteration":16,"passed_time":0.01222503585,"remaining_time":0.1315989154},
{"learn":[0.5461163358],"iteration":17,"passed_time":0.01308345195,"remaining_time":0.1322882363},
{"learn":[0.5393248527],"iteration":18,"passed_time":0.01467819948,"remaining_time":0.1398291635},
{"learn":[0.5348603495],"iteration":19,"passed_time":0.01582496957,"remaining_time":0.1424247261},
{"learn":[0.5326056063],"iteration":20,"passed_time":0.0175517845,"remaining_time":0.1496080679},
{"learn":[0.5290347734],"iteration":21,"passed_time":0.01835916078,"remaining_time":0.1485423008},
{"learn":[0.5244750013],"iteration":22,"passed_time":0.0190094818,"remaining_time":0.1462903599},
{"learn":[0.5186705076],"iteration":23,"passed_time":0.01964326576,"remaining_time":0.1440506156},
{"learn":[0.5142362126],"iteration":24,"passed_time":0.02031298387,"remaining_time":0.1421908871},
{"learn":[0.511871039],"iteration":25,"passed_time":0.02097486448,"remaining_time":0.1403702469},
{"learn":[0.5084618594],"iteration":26,"passed_time":0.02159559463,"remaining_time":0.138371773},
{"learn":[0.5041277546],"iteration":27,"passed_time":0.02219544245,"remaining_time":0.1363434322},
{"learn":[0.5014024587],"iteration":28,"passed_time":0.02281965853,"remaining_time":0.1345572969},
{"learn":[0.4989179377],"iteration":29,"passed_time":0.02350247715,"remaining_time":0.1331807038},
{"learn":[0.4960043448],"iteration":30,"passed_time":0.0241397641,"remaining_time":0.1316006495},
{"learn":[0.4934192751],"iteration":31,"passed_time":0.02484394906,"remaining_time":0.1304307325},
{"learn":[0.4901659879],"iteration":32,"passed_time":0.02551281139,"remaining_time":0.129110288},
{"learn":[0.487502835],"iteration":33,"passed_time":0.02615001843,"remaining_time":0.1276736194},
{"learn":[0.485060597],"iteration":34,"passed_time":0.02683907705,"remaining_time":0.1265270775},
{"learn":[0.4831842649],"iteration":35,"passed_time":0.02747470905,"remaining_time":0.1251625634},
{"learn":[0.4797936521],"iteration":36,"passed_time":0.02809288357,"remaining_time":0.1237605411},
{"learn":[0.4759946145],"iteration":37,"passed_time":0.02873273244,"remaining_time":0.1224921752},
{"learn":[0.4745018494],"iteration":38,"passed_time":0.02938586142,"remaining_time":0.1213108638},
{"learn":[0.4727868322],"iteration":39,"passed_time":0.03079088548,"remaining_time":0.1231635419},
{"learn":[0.4702990779],"iteration":40,"passed_time":0.03386479902,"remaining_time":0.1313293425},
{"learn":[0.4693032708],"iteration":41,"passed_time":0.03547013813,"remaining_time":0.1334352816},
{"learn":[0.4674717328],"iteration":42,"passed_time":0.03639673183,"remaining_time":0.132890393},
{"learn":[0.4655995515],"iteration":43,"passed_time":0.03729967116,"remaining_time":0.1322442887},
{"learn":[0.4641216197],"iteration":44,"passed_time":0.03820267065,"remaining_time":0.1315869767},
{"learn":[0.4598561171],"iteration":45,"passed_time":0.0391510258,"remaining_time":0.1310708255},
{"learn":[0.4585498923],"iteration":46,"passed_time":0.04017564389,"remaining_time":0.1307845429},
{"learn":[0.4559679895],"iteration":47,"passed_time":0.04108267258,"remaining_time":0.1300951298},
{"learn":[0.4533795452],"iteration":48,"passed_time":0.04208851318,"remaining_time":0.1297013365},
{"learn":[0.4506573946],"iteration":49,"passed_time":0.04318329609,"remaining_time":0.1295498883},
{"learn":[0.4498053536],"iteration":50,"passed_time":0.0444972281,"remaining_time":0.1300017056},
{"learn":[0.4464470419],"iteration":51,"passed_time":0.04593527598,"remaining_time":0.1307388624},
{"learn":[0.4449380715],"iteration":52,"passed_time":0.04762302914,"remaining_time":0.1320865148},
{"learn":[0.4424900298],"iteration":53,"passed_time":0.04851571363,"remaining_time":0.1311721146},
{"learn":[0.4415586329],"iteration":54,"passed_time":0.04947596152,"remaining_time":0.1304366258},
{"learn":[0.4397157647],"iteration":55,"passed_time":0.0511467062,"remaining_time":0.1315201016},
{"learn":[0.4370424254],"iteration":56,"passed_time":0.05201582521,"remaining_time":0.1304958422},
{"learn":[0.4352948313],"iteration":57,"passed_time":0.05268196759,"remaining_time":0.1289799896},
{"learn":[0.4331723785],"iteration":58,"passed_time":0.0533250752,"remaining_time":0.1274378916},
{"learn":[0.4313788669],"iteration":59,"passed_time":0.05398382907,"remaining_time":0.1259622678},
{"learn":[0.4292841658],"iteration":60,"passed_time":0.05465043122,"remaining_time":0.1245313105},
{"learn":[0.4280419684],"iteration":61,"passed_time":0.05533553068,"remaining_time":0.1231661812},
{"learn":[0.4268497172],"iteration":62,"passed_time":0.05612997616,"remaining_time":0.1220604244},
{"learn":[0.4249768646],"iteration":63,"passed_time":0.05685715189,"remaining_time":0.1208214478},
{"learn":[0.4239215672],"iteration":64,"passed_time":0.05753860469,"remaining_time":0.1195032559},
{"learn":[0.4231713625],"iteration":65,"passed_time":0.05821657874,"remaining_time":0.1181972962},
{"learn":[0.4214033819],"iteration":66,"passed_time":0.05888366848,"remaining_time":0.1168884762},
{"learn":[0.4196842072],"iteration":67,"passed_time":0.05956266802,"remaining_time":0.1156216497},
{"learn":[0.4176707771],"iteration":68,"passed_time":0.06049227172,"remaining_time":0.1148476463},
{"learn":[0.4152847543],"iteration":69,"passed_time":0.06195628894,"remaining_time":0.1150616795},
{"learn":[0.4127036667],"iteration":70,"passed_time":0.0629944691,"remaining_time":0.1144547396},
{"learn":[0.4111162419],"iteration":71,"passed_time":0.06391540558,"remaining_time":0.1136273877},
{"learn":[0.4092206357],"iteration":72,"passed_time":0.06500974399,"remaining_time":0.1130991437},
{"learn":[0.4082956822],"iteration":73,"passed_time":0.06625083882,"remaining_time":0.1128054823},
{"learn":[0.4071857474],"iteration":74,"passed_time":0.06731974937,"remaining_time":0.1121995823},
{"learn":[0.4056018623],"iteration":75,"passed_time":0.0682987056,"remaining_time":0.1114347302},
{"learn":[0.4051266178],"iteration":76,"passed_time":0.06974072161,"remaining_time":0.1114040098},
{"learn":[0.4040431706],"iteration":77,"passed_time":0.07098990986,"remaining_time":0.1110355},
{"learn":[0.403177115],"iteration":78,"passed_time":0.0719513745,"remaining_time":0.110204004},
{"learn":[0.4019096866],"iteration":79,"passed_time":0.0728579111,"remaining_time":0.1092868666},
{"learn":[0.4011194577],"iteration":80,"passed_time":0.07377760209,"remaining_time":0.1083893166},
{"learn":[0.3995326357],"iteration":81,"passed_time":0.07479794763,"remaining_time":0.107636071},
{"learn":[0.3976884622],"iteration":82,"passed_time":0.07659802269,"remaining_time":0.107975526},
{"learn":[0.3967044199],"iteration":83,"passed_time":0.07758754266,"remaining_time":0.1071447018},
{"learn":[0.3955409853],"iteration":84,"passed_time":0.07853082157,"remaining_time":0.1062475821},
{"learn":[0.3948310509],"iteration":85,"passed_time":0.07946686373,"remaining_time":0.1053397961},
{"learn":[0.3928982333],"iteration":86,"passed_time":0.08077697487,"remaining_time":0.1049172202},
{"learn":[0.3913250623],"iteration":87,"passed_time":0.0824067451,"remaining_time":0.1048813119},
{"learn":[0.388668313],"iteration":88,"passed_time":0.08349739285,"remaining_time":0.1041371978},
{"learn":[0.3869571485],"iteration":89,"passed_time":0.08468573364,"remaining_time":0.1035047856},
{"learn":[0.385020302],"iteration":90,"passed_time":0.08615046834,"remaining_time":0.1031912203},
{"learn":[0.3842317234],"iteration":91,"passed_time":0.08716421109,"remaining_time":0.1023232043},
{"learn":[0.3833728074],"iteration":92,"passed_time":0.08811702108,"remaining_time":0.101381949},
{"learn":[0.3817631161],"iteration":93,"passed_time":0.08916773961,"remaining_time":0.1005508553},
{"learn":[0.3809495428],"iteration":94,"passed_time":0.09008180301,"remaining_time":0.09956409807},
{"learn":[0.3803791219],"iteration":95,"passed_time":0.09148576747,"remaining_time":0.09910958143},
{"learn":[0.3788537654],"iteration":96,"passed_time":0.0924360784,"remaining_time":0.09815377397},
{"learn":[0.3777605592],"iteration":97,"passed_time":0.09320260953,"remaining_time":0.09700679768},
{"learn":[0.377058758],"iteration":98,"passed_time":0.09389677851,"remaining_time":0.09579368313},
{"learn":[0.3759466717],"iteration":99,"passed_time":0.09456177598,"remaining_time":0.09456177598},
{"learn":[0.3753518497],"iteration":100,"passed_time":0.09524389148,"remaining_time":0.09335787383},
{"learn":[0.3747594498],"iteration":101,"passed_time":0.09595593997,"remaining_time":0.09219296193},
{"learn":[0.3734599353],"iteration":102,"passed_time":0.09662495586,"remaining_time":0.09099631766},
{"learn":[0.372723599],"iteration":103,"passed_time":0.09729911623,"remaining_time":0.08981456883},
{"learn":[0.3715554266],"iteration":104,"passed_time":0.09794837675,"remaining_time":0.08861995991},
{"learn":[0.3698975921],"iteration":105,"passed_time":0.09862759449,"remaining_time":0.08746220644},
{"learn":[0.3688404477],"iteration":106,"passed_time":0.09927513629,"remaining_time":0.08628586612},
{"learn":[0.3672861851],"iteration":107,"passed_time":0.09992922968,"remaining_time":0.08512489936},
{"learn":[0.3663182332],"iteration":108,"passed_time":0.1005807315,"remaining_time":0.08397106945},
{"learn":[0.3640346919],"iteration":109,"passed_time":0.1012395653,"remaining_time":0.08283237163},
{"learn":[0.3627194496],"iteration":110,"passed_time":0.1019385124,"remaining_time":0.08173448292},
{"learn":[0.3611892407],"iteration":111,"passed_time":0.1029116157,"remaining_time":0.08085912659},
{"learn":[0.3591365476],"iteration":112,"passed_time":0.1040176942,"remaining_time":0.08008441939},
{"learn":[0.3576690125],"iteration":113,"passed_time":0.1053637583,"remaining_time":0.07948494046},
{"learn":[0.3571680796],"iteration":114,"passed_time":0.1061544116,"remaining_time":0.07846195643},
{"learn":[0.3561367614],"iteration":115,"passed_time":0.1068692331,"remaining_time":0.07738806532},
{"learn":[0.3551807673],"iteration":116,"passed_time":0.1076033322,"remaining_time":0.07633398777},
{"learn":[0.3540785899],"iteration":117,"passed_time":0.1083113083,"remaining_time":0.07526718038},
{"learn":[0.3531172619],"iteration":118,"passed_time":0.1089761343,"remaining_time":0.07417703259},
{"learn":[0.3509590117],"iteration":119,"passed_time":0.1096843395,"remaining_time":0.07312289298},
{"learn":[0.3501333604],"iteration":120,"passed_time":0.110361632,"remaining_time":0.07205428864},
{"learn":[0.348699121],"iteration":121,"passed_time":0.1110258042,"remaining_time":0.07098371088},
{"learn":[0.3470968811],"iteration":122,"passed_time":0.1117461553,"remaining_time":0.06995491025},
{"learn":[0.346151927],"iteration":123,"passed_time":0.1124732898,"remaining_time":0.06893524211},
{"learn":[0.3448782721],"iteration":124,"passed_time":0.1146575611,"remaining_time":0.06879453668},
{"learn":[0.3435579659],"iteration":125,"passed_time":0.1157347285,"remaining_time":0.06797118977},
{"learn":[0.3423861689],"iteration":126,"passed_time":0.1166985611,"remaining_time":0.06707870048},
{"learn":[0.3411925302],"iteration":127,"passed_time":0.117830547,"remaining_time":0.06627968269},
{"learn":[0.3400637361],"iteration":128,"passed_time":0.1190239919,"remaining_time":0.06550932885},
{"learn":[0.3387540639],"iteration":129,"passed_time":0.1200833076,"remaining_time":0.06466024254},
{"learn":[0.3379454574],"iteration":130,"passed_time":0.1213128105,"remaining_time":0.06389758721},
{"learn":[0.3363421445],"iteration":131,"passed_time":0.1222750725,"remaining_time":0.06299018888},
{"learn":[0.3345148672],"iteration":132,"passed_time":0.1232067218,"remaining_time":0.06206654407},
{"learn":[0.3326417844],"iteration":133,"passed_time":0.1241485514,"remaining_time":0.06114779397},
{"learn":[0.3319223877],"iteration":134,"passed_time":0.1250142626,"remaining_time":0.06019205236},
{"learn":[0.3313807323],"iteration":135,"passed_time":0.1259240687,"remaining_time":0.05925838528},
{"learn":[0.330143168],"iteration":136,"passed_time":0.1268522348,"remaining_time":0.05833350942},
{"learn":[0.3295822374],"iteration":137,"passed_time":0.1279697013,"remaining_time":0.05749363394},
{"learn":[0.3287697469],"iteration":138,"passed_time":0.1288972532,"remaining_time":0.05656642046},
{"learn":[0.3273743428],"iteration":139,"passed_time":0.129795876,"remaining_time":0.05562680398},
{"learn":[0.3256292429],"iteration":140,"passed_time":0.1306496828,"remaining_time":0.05466901619},
{"learn":[0.3245198693],"iteration":141,"passed_time":0.1316672078,"remaining_time":0.05377956374},
{"learn":[0.3233961661],"iteration":142,"passed_time":0.1329893589,"remaining_time":0.05300974446},
{"learn":[0.3218521245],"iteration":143,"passed_time":0.1344198602,"remaining_time":0.05227439009},
{"learn":[0.3203590091],"iteration":144,"passed_time":0.1353263798,"remaining_time":0.05133069578},
{"learn":[0.3195481386],"iteration":145,"passed_time":0.1360186765,"remaining_time":0.0503082776},
{"learn":[0.3189725371],"iteration":146,"passed_time":0.1366900199,"remaining_time":0.0492827963},
{"learn":[0.3183775295],"iteration":147,"passed_time":0.137445735,"remaining_time":0.04829174472},
{"learn":[0.3180816739],"iteration":148,"passed_time":0.1381166995,"remaining_time":0.04727484344},
{"learn":[0.3169809247],"iteration":149,"passed_time":0.1389097504,"remaining_time":0.04630325013},
{"learn":[0.3162238234],"iteration":150,"passed_time":0.1396342053,"remaining_time":0.04531176198},
{"learn":[0.314466308],"iteration":151,"passed_time":0.1402849043,"remaining_time":0.04430049611},
{"learn":[0.3135258728],"iteration":152,"passed_time":0.1409276698,"remaining_time":0.04329150641},
{"learn":[0.3127494911],"iteration":153,"passed_time":0.1416481646,"remaining_time":0.04231049073},
{"learn":[0.3111535863],"iteration":154,"passed_time":0.142316604,"remaining_time":0.04131772375},
{"learn":[0.309693421],"iteration":155,"passed_time":0.1429778156,"remaining_time":0.04032707621},
{"learn":[0.3081834755],"iteration":156,"passed_time":0.1436486688,"remaining_time":0.03934326597},
{"learn":[0.3063244619],"iteration":157,"passed_time":0.1443459133,"remaining_time":0.03837043265},
{"learn":[0.304639244],"iteration":158,"passed_time":0.1450415657,"remaining_time":0.03740065532},
{"learn":[0.3029583402],"iteration":159,"passed_time":0.145782185,"remaining_time":0.03644554625},
{"learn":[0.3013946356],"iteration":160,"passed_time":0.1466489172,"remaining_time":0.03552365075},
{"learn":[0.3001100724],"iteration":161,"passed_time":0.1475524959,"remaining_time":0.03461107928},
{"learn":[0.298910168],"iteration":162,"passed_time":0.1486468837,"remaining_time":0.03374193065},
{"learn":[0.2987595513],"iteration":163,"passed_time":0.1502197584,"remaining_time":0.03297506892},
{"learn":[0.2973205239],"iteration":164,"passed_time":0.1512969591,"remaining_time":0.03209329435},
{"learn":[0.2971198248],"iteration":165,"passed_time":0.1524084873,"remaining_time":0.0312161962},
{"learn":[0.2959703932],"iteration":166,"passed_time":0.1533860454,"remaining_time":0.03030981736},
{"learn":[0.2947071095],"iteration":167,"passed_time":0.154099977,"remaining_time":0.02935237656},
{"learn":[0.2935494052],"iteration":168,"passed_time":0.1547431349,"remaining_time":0.02838483539},
{"learn":[0.2933051709],"iteration":169,"passed_time":0.1554014712,"remaining_time":0.02742378903},
{"learn":[0.2932300611],"iteration":170,"passed_time":0.156188705,"remaining_time":0.02648814296},
{"learn":[0.2923365347],"iteration":171,"passed_time":0.1570463677,"remaining_time":0.02556568777},
{"learn":[0.2920285854],"iteration":172,"passed_time":0.1579713711,"remaining_time":0.02465449145},
{"learn":[0.2917127245],"iteration":173,"passed_time":0.1586805811,"remaining_time":0.02371089143},
{"learn":[0.2906202038],"iteration":174,"passed_time":0.1593254847,"remaining_time":0.02276078353},
{"learn":[0.2900615866],"iteration":175,"passed_time":0.1600528481,"remaining_time":0.02182538838},
{"learn":[0.2883316525],"iteration":176,"passed_time":0.1609239238,"remaining_time":0.02091101835},
{"learn":[0.2875370613],"iteration":177,"passed_time":0.1620704828,"remaining_time":0.02003118327},
{"learn":[0.2861976728],"iteration":178,"passed_time":0.1633562455,"remaining_time":0.01916469919},
{"learn":[0.2847951914],"iteration":179,"passed_time":0.164473642,"remaining_time":0.01827484911},
{"learn":[0.2836745821],"iteration":180,"passed_time":0.1652934947,"remaining_time":0.01735125083},
{"learn":[0.2821050444],"iteration":181,"passed_time":0.1659878684,"remaining_time":0.01641638259},
{"learn":[0.2818080899],"iteration":182,"passed_time":0.1669110651,"remaining_time":0.01550539949},
{"learn":[0.2810216534],"iteration":183,"passed_time":0.1680411877,"remaining_time":0.01461227719},
{"learn":[0.2808722851],"iteration":184,"passed_time":0.169296431,"remaining_time":0.01372673765},
{"learn":[0.279865803],"iteration":185,"passed_time":0.1705069337,"remaining_time":0.01283385522},
{"learn":[0.2797331266],"iteration":186,"passed_time":0.1714776052,"remaining_time":0.01192090304},
{"learn":[0.279420771],"iteration":187,"passed_time":0.1725871086,"remaining_time":0.01101619842},
{"learn":[0.2788294068],"iteration":188,"passed_time":0.1740384617,"remaining_time":0.01012922264},
{"learn":[0.2776244879],"iteration":189,"passed_time":0.1757360531,"remaining_time":0.009249265951},
{"learn":[0.2767829437],"iteration":190,"passed_time":0.177500159,"remaining_time":0.008363881836},
{"learn":[0.2758183897],"iteration":191,"passed_time":0.1793713031,"remaining_time":0.007473804296},
{"learn":[0.2749429281],"iteration":192,"passed_time":0.1804727032,"remaining_time":0.006545642084},
{"learn":[0.2735619829],"iteration":193,"passed_time":0.1822543958,"remaining_time":0.005636733892},
{"learn":[0.2723099832],"iteration":194,"passed_time":0.1833271515,"remaining_time":0.004700696193},
{"learn":[0.2717861245],"iteration":195,"passed_time":0.1842272281,"remaining_time":0.003759739349},
{"learn":[0.2703384384],"iteration":196,"passed_time":0.1851648633,"remaining_time":0.002819769491},
{"learn":[0.2690198319],"iteration":197,"passed_time":0.1860220159,"remaining_time":0.001879010262},
{"learn":[0.268349301],"iteration":198,"passed_time":0.1871398444,"remaining_time":0.000940401228},
{"learn":[0.2681392011],"iteration":199,"passed_time":0.1881510288,"remaining_time":0}
]}